pygutils/__init__.py
pygutils/animation/__init__.py
pygutils/animation/animation.py
pygutils/animation/animation_contract.py
pygutils/camera/__init__.py
pygutils/camera/camera_2d.py
pygutils/event/__init__.py
pygutils/event/event_listener.py
pygutils/event/event_manager.py
pygutils/sprite/__init__.py
pygutils/sprite/sprite_sheet.py
pygutils/timer/__init__.py
pygutils/timer/timer.py
test/__init__.py
test/animation_test.py
test/timer_test.py
test/camera/__init__.py
test/camera/camera_2d_test.py
test/event/__init__.py
test/event/event_listener_test.py
test/event/event_manager_test.py
test/sprite/__init__.py
test/sprite/sprite_sheet_test.py
pygutils-0.3.0.dist-info/LICENSE
pygutils-0.3.0.dist-info/METADATA
pygutils-0.3.0.dist-info/WHEEL
pygutils-0.3.0.dist-info/top_level.txt
pygutils-0.3.0.dist-info/RECORD
