Metadata-Version: 2.1
Name: pygutils
Version: 0.3.0
Summary: Package with utility functions and classes to work with Pygame.
Author: Lucas Eliaquim
Author-email: <lemsantos.dev@gmail.com>
License: MIT
Project-URL: Bug Tracker, https://github.com/LEMSantos/pygutils/issues
Project-URL: Source, https://github.com/LEMSantos/pygutils
Keywords: python,pygame,utility,helpers
Classifier: Development Status :: 3 - Alpha
Classifier: Intended Audience :: Developers
Classifier: Programming Language :: Python :: 3
Classifier: Operating System :: Unix
Classifier: Operating System :: MacOS :: MacOS X
Classifier: Operating System :: Microsoft :: Windows
Requires-Python: >=3.10
License-File: LICENSE
Requires-Dist: pygame
